{
    "tafseer_id": 4,
    "tafseer_name": "تفسير ابن كثير",
    "ayah_url": "/quran/5/17/",
    "ayah_number": 17,
    "text": "يقول تعالى مخبرا وحاكما بكفر النصارى في ادعائهم في المسيح ابن مريم - وهو عبد من عباد الله ، وخلق من خلقه - أنه هو الله الحكم بكفر النصارى ، تعالى الله عن قولهم علوا كبيرا .ثم قال مخبرا عن قدرته على الأشياء وكونها تحت قهره وسلطانه : ( قل فمن يملك من الله شيئا إن أراد أن يهلك المسيح ابن مريم وأمه ومن في الأرض جميعا ) أي : لو أراد ذلك ، فمن ذا الذي كان يمنعه ؟ أو من ذا الذي يقدر على صرفه عن ذلك؟ثم قال : ( ولله ملك السماوات والأرض وما بينهما يخلق ما يشاء ) أي : جميع الموجودات ملكه وخلقه ، وهو القادر على ما يشاء ، لا يسأل عما يفعل ، لقدرته وسلطانه ، وعدله وعظمته ، وهذا رد على النصارى عليهم لعائن الله المتتابعة إلى يوم القيامة ."
}