{
    "tafseer_id": 5,
    "tafseer_name": "تفسير الوسيط لطنطاوي",
    "ayah_url": "/quran/41/53/",
    "ayah_number": 53,
    "text": "ثم بين- سبحانه- أن حكمته قد اقتضت أن يطلع الناس في كل زمان ومكان على دلائل وحدانيته وقدرته، وعلى صدق رسوله صلّى الله عليه وسلم فيما بلغه عنه، فقال: سَنُرِيهِمْ آياتِنا فِي الْآفاقِ وَفِي أَنْفُسِهِمْ حَتَّى يَتَبَيَّنَ لَهُمْ أَنَّهُ الْحَقُّ ...والمراد بالآيات في قوله آياتِنا: الدلائل والبراهين الدالة على وحدانيته- سبحانه- وعلى صدق رسوله صلّى الله عليه وسلم.والآفاق: جمع أفق- كأعناق جمع عنق- وهو الناحية والجهة، يقال: أفق فلان يأفق- كضرب يضرب- إذا سار في آفاق الأرض وجهاتها المتعددة.والمعنى: سنطلع الناس على دلائل وحدانيتنا وقدرتنا في أقطار السموات والأرض، من شمس وقمر ونجوم، وليل ونهار، ورياح وأمطار، وزرع وثمار، ورعد وبرق وصواعق، وجبال وبحار.سنطلعهم على مظاهر قدرتنا في هذه الأشياء الخارجية التي يرونها بأعينهم، كما سنطلعهم على آثار قدرتنا في أنفسهم عن طريق ما أودعنا فيهم من حواس وقوى، وعقل، وروح، وعن طريق ما يصيبهم من خير وشر، ونعمة ونقمة.ولقد صدق الله- تعالى- وعده، ففي كل يوم بل في كل ساعة، يطلع الناس على أسرار جديدة في هذا الكون الهائل، وفي أنفسهم.. وكلها تدل على وحدانيته، - تعالى- وقدرته، وعلى صحة دين الإسلام الذي جاء به الرسول عليه الصلاة والسلام.وقوله- تعالى-: أَوَلَمْ يَكْفِ بِرَبِّكَ أَنَّهُ عَلى كُلِّ شَيْءٍ شَهِيدٌ استئناف مسوق لتوبيخ الكافرين على عنادهم مع ظهور الأدلة على أن ما جاء به الرسول صلّى الله عليه وسلم من عند ربه هو الحق المبين.والهمزة للإنكار، والواو للعطف على مقدر يقتضيه المقام، والباء مزيدة للتأكيد، وقوله بِرَبِّكَ فاعل كفى.والمعنى: ألم يغن هؤلاء الجاحدين عن الآيات الموعودة الدالة على صحة هذا الدين، أن ربك- أيها الرسول الكريم- شهيد على كل شيء، وعلى أنك صادق فيما تبلغه عنه.. بلى.إن في شهادة ربك وعلمه بكل شيء ما يغنيك عن كل شيء سواه."
}