{
    "tafseer_id": 5,
    "tafseer_name": "تفسير الوسيط لطنطاوي",
    "ayah_url": "/quran/6/67/",
    "ayah_number": 67,
    "text": "ثم ختم هذا التهديد بقوله- تعالى- لِكُلِّ نَبَإٍ مُسْتَقَرٌّ وَسَوْفَ تَعْلَمُونَ.قال الراغب: «النبأ: خبر ذو فائدة عظيمة يحصل به علم أو غلبة ظن ولا يقال للخبر نبأ حق يتضمن هذه الأشياء الثلاثة» .والمستقر: وقت الاستقرار.أى: لكل خبر عظيم وقت استقرار وحصول لا بد منه، وسوف تعلمونه في المستقبل عند حلوله بكم متى شاء الله ذلك، قال- تعالى- وَلَتَعْلَمُنَّ نَبَأَهُ بَعْدَ حِينٍ.وبذلك تكون الآيات الكريمة قد ساقت ألوانا من قدرة الله، وهددت المعاندين في كل زمان ومكان بسوء المصير."
}