{
    "tafseer_id": 5,
    "tafseer_name": "تفسير الوسيط لطنطاوي",
    "ayah_url": "/quran/26/8/",
    "ayah_number": 8,
    "text": "ثم ختم- سبحانه- هذه الآيات بآيتين تكررتا في السورة الكريمة ثماني مرات. ألا وهما قوله- تعالى- إِنَّ فِي ذلِكَ لَآيَةً وَما كانَ أَكْثَرُهُمْ مُؤْمِنِينَ، وَإِنَّ رَبَّكَ لَهُوَ الْعَزِيزُ الرَّحِيمُ.أى: إن في ذلك الذي ذكرناه عن إنباتنا لكل زوج كريم في الأرض لَآيَةً عظيمة الدلالة على كمال قدرتنا، وسعة رحمتنا، وما كان أكثر هؤلاء الكافرين مؤمنين، لإيثارهم العمى على الهدى، والغي على الرشد"
}