{
    "tafseer_id": 5,
    "tafseer_name": "تفسير الوسيط لطنطاوي",
    "ayah_url": "/quran/20/20/",
    "ayah_number": 20,
    "text": "فَأَلْقاها فَإِذا هِيَ حَيَّةٌ تَسْعى.أى: فامتثل موسى أمر ربه، فألقاها على الأرض، ونظر إليها فإذا هي قد تحولت بقدرة الله- تعالى- إلى «حية» - أى ثعبان عظيم- «تسعى» ، أى: تمشى على الأرض بسرعة وخفة حركة ووصفها- سبحانه- هنا بأنها حَيَّةٌ تَسْعى، ووصفها في سورة الشعراء بأنها ثُعْبانٌ مُبِينٌ  ووصفها في سورة النمل بأنها تَهْتَزُّ كَأَنَّها جَانٌّ  .ولا تنافى بين هذه الأوصاف، لأن الحية اسم جنس يطلق على الصغير والكبير، والذكر والأنثى، والثعبان: هو العظيم منها، والجان: هو الحية الصغيرة الجسم، السريعة الحركة.وقد صرحت بعض الآيات أن موسى- عليه السلام- عند ما رأى عصاه قد تحولت إلى ذلك، ولى مدبرا ولم يعقب. قال- تعالى-: وَأَنْ أَلْقِ عَصاكَ فَلَمَّا رَآها تَهْتَزُّ كَأَنَّها جَانٌّ وَلَّى مُدْبِراً وَلَمْ يُعَقِّبْ ..."
}