{
    "tafseer_id": 4,
    "tafseer_name": "تفسير ابن كثير",
    "ayah_url": "/quran/82/19/",
    "ayah_number": 19,
    "text": "ثم فسره بقوله ( يوم لا تملك نفس لنفس شيئا والأمر يومئذ لله ) أي : لا يقدر واحد على نفع أحد ولا خلاصه مما هو فيه إلا أن يأذن الله لمن يشاء ويرضىونذكر هاهنا حديث يا بني هاشم أنقذوا أنفسكم من النار لا أملك لكم من الله شيئا وقد تقدم في آخر تفسير سورة الشعراء ولهذا قال ( والأمر يومئذ لله ) كقوله ( لمن الملك اليوم لله الواحد القهار ) غافر 16 وكقوله ( الملك يومئذ الحق للرحمن ) الفرقان : 26 وكقوله ( مالك يوم الدين ) الفاتحة : 4قال قتادة : ( يوم لا تملك نفس لنفس شيئا والأمر يومئذ لله والأمر والله اليوم لله ولكنه يومئذ لا ينازعه أحدآخر تفسير سورة الانفطار ولله الحمد"
}