{
    "tafseer_id": 8,
    "tafseer_name": "تفسير الطبري",
    "ayah_url": "/quran/76/27/",
    "ayah_number": 27,
    "text": "وقوله : ( إن هؤلاء يحبون العاجلة ) يقول تعالى ذكره : إن هؤلاء المشركين بالله يحبون العاجلة ، يعني ، الدنيا ، يقول : يحبون البقاء فيها وتعجبهم زينتها ( ويذرون وراءهم يوما ثقيلا ) يقول : ويدعون خلف ظهورهم العمل للآخرة ، وما لهم فيه النجاة من عذاب الله يومئذ ، وقد تأوله بعضهم بمعنى : ويذرون أمامهم يوما ثقيلا وليس ذلك قولا مدفوعا ، غير أن الذي قلناه أشبه بمعنى الكلمة .وبنحو الذي قلنا في ذلك قال أهل التأويل .ذكر من قال ذلك :حدثنا ابن حميد ، قال : ثنا مهران ، عن سفيان ( ويذرون وراءهم يوما ثقيلا ) قال : الآخرة ."
}