{
    "tafseer_id": 4,
    "tafseer_name": "تفسير ابن كثير",
    "ayah_url": "/quran/9/44/",
    "ayah_number": 44,
    "text": "يقول تعالى : هلا تركتهم لما استأذنوك ، فلم تأذن لأحد منهم في القعود ، لتعلم الصادق منهم في إظهار طاعتك من الكاذب ، فإنهم قد كانوا مصرين على القعود عن الغزو [ وإن لم تأذن لهم فيه . ولهذا أخبر تعالى أنه لا يستأذنه في القعود عن الغزو ] أحد يؤمن بالله ورسوله ، فقال : ( لا يستأذنك ) أي : في القعود عن الغزو ( الذين يؤمنون بالله واليوم الآخر أن يجاهدوا بأموالهم وأنفسهم ) ؛ لأن أولئك يرون الجهاد قربة ، ولما ندبهم إليه بادروا وامتثلوا ."
}