{
    "tafseer_id": 5,
    "tafseer_name": "تفسير الوسيط لطنطاوي",
    "ayah_url": "/quran/34/47/",
    "ayah_number": 47,
    "text": "ثم أمره- سبحانه- للمرة الثانية أن يصارحهم بأنه لا يريد منهم أجرا على دعوته إياهم إلى ما يسعدهم فقال: قُلْ ما سَأَلْتُكُمْ مِنْ أَجْرٍ فَهُوَ لَكُمْ إِنْ أَجْرِيَ إِلَّا عَلَى اللَّهِ، وَهُوَ عَلى كُلِّ شَيْءٍ شَهِيدٌ.أى: وقل لهم- أيها الرسول الكريم. بعد أن دعوتهم إلى التفكير الهادئ، المتأنى في أمرك: إنى ما طلبت منكم أجرا على دعوتي إياكم إلى الحق والخير، وإذا فرض وطلبت فهو مردود عليكم. لأنى لا ألتمس أجرى إلا من الله- تعالى- وحده، وهو- سبحانه- على كل شيء شهيد ورقيب، ولا يخفى عليه شيء في الأرض ولا في السماء.قال الآلوسى قوله: قل ما سألتكم من أجر، أى: مهما سألتكم من نفع على تبليغ الرسالة فَهُوَ لَكُمْ والمراد نفى السؤال رأسا، كقولك لصاحبك إن أعطيتنى شيئا فخذه، وأنت تعلم أنه لم يعطك شيئا: فما شرطية. مفعول سَأَلْتُكُمْ وقوله فَهُوَ لَكُمْ الجواب- وقيل هي موصولة، والعائد محذوف، ومن للبيان ودخلت الفاء في الخبر لتضمنها معنى الشرط. أى: الذي سألتكموه من الأجر فهو لكم، وثمرته تعود إليكم ."
}