{
    "tafseer_id": 5,
    "tafseer_name": "تفسير الوسيط لطنطاوي",
    "ayah_url": "/quran/52/13/",
    "ayah_number": 13,
    "text": "ثم بين- سبحانه- حالهم يوم القيامة فقال: يَوْمَ يُدَعُّونَ إِلى نارِ جَهَنَّمَ دَعًّا، هذِهِ النَّارُ الَّتِي كُنْتُمْ بِها تُكَذِّبُونَ.والدع: الدفع بعنف وشدة. يقال: دعّ فلان فلانا دعّا، إذا دفعه بجفوة وغلظة، ومنه قوله- تعالى-: أَرَأَيْتَ الَّذِي يُكَذِّبُ بِالدِّينِ. فَذلِكَ الَّذِي يَدُعُّ الْيَتِيمَ.أى: اذكر- أيها العاقل- لتعتبر وتتعظ، يوم يدفع هؤلاء المكذبون إلى النار دفعا قويا.لا رحمة معه، ولا شفقة فيه،"
}