{
    "tafseer_id": 5,
    "tafseer_name": "تفسير الوسيط لطنطاوي",
    "ayah_url": "/quran/39/32/",
    "ayah_number": 32,
    "text": "والفاء في قوله- تعالى-: فَمَنْ أَظْلَمُ مِمَّنْ كَذَبَ عَلَى اللَّهِ ... لترتيب ما بعدها على ما قبلها، والاستفهام للإنكار والنفي.أى مادام الأمر كما ذكرنا لك- أيها الرسول الكريم- من أنك ستموت وهم سيموتون، وأنكم جميعا ستقفون أمام ربكم للحساب والجزاء.. فلا أحد أشد ظلما من هؤلاء المشركين الذين كذبوا على الله، بأن عبدوا من دونه آلهة أخرى، ونسبوا إليه الشريك أو الولد، ولم يكتفوا بكل ذلك، بل كذبوا بالأمر الصدق وقت أن جئتهم به من عند ربك.والتعبير بقوله: وَكَذَّبَ بِالصِّدْقِ إِذْ جاءَهُ يدل على أنهم بادروا بتكذيب ما جاءهم به الرسول صلّى الله عليه وسلم من عند ربه، بمجرد أن سمعوه، ودون أن يتدبروه أو يفكروا فيه.وتكذيبهم بالصدق، يشمل تكذيبهم للقرآن الكريم، ولكل ما جاءهم به الرسول صلّى الله عليه وسلم والاستفهام في قوله- تعالى- أَلَيْسَ فِي جَهَنَّمَ مَثْوىً لِلْكافِرِينَ للتقرير.والمثوى: المكان مأخوذ من قولهم ثوى فلان بمكان كذا، إذا أقام به. يقال: ثوى يثوى ثواء، كمضى يمضى مضاء ...أى: أليس في جهنم مكانا يكفى لإهانة الكافرين وإذلالهم وتعذيبهم؟ بل إن فيها لمكانا يذلهم ويذوقون فيه سوء العذاب."
}