{
    "tafseer_id": 5,
    "tafseer_name": "تفسير الوسيط لطنطاوي",
    "ayah_url": "/quran/27/78/",
    "ayah_number": 78,
    "text": "ثم بين- سبحانه- أن مرد القضاء بين المختلفين إليه وحده فقال: إِنَّ رَبَّكَ يَقْضِي بَيْنَهُمْ بِحُكْمِهِ ...أى: إن ربك- أيها الرسول الكريم- يقضى بين بنى إسرائيل الذين اختلفوا فيما بينهم اختلافا كبيرا، بحكمه العادل، كما يقضى بين غيرهم، فيجازى الذين أساؤوا بما عملوا، ويجازى الذين أحسنوا بالحسنى.وَهُوَ- سبحانه- الْعَزِيزُ الذي لا يغالب الْعَلِيمُ بكل شيء في هذا الوجود،"
}